greenland/bundle/__init__.py
greenland5-0.0.1.dist-info/AUTHORS
greenland5-0.0.1.dist-info/LICENSE
greenland5-0.0.1.dist-info/METADATA
greenland5-0.0.1.dist-info/WHEEL
greenland5-0.0.1.dist-info/top_level.txt
greenland5-0.0.1.dist-info/RECORD
