Metadata-Version: 2.1
Name: greenland5
Version: 0.0.1
Summary: Greenland5 Root Package - Pulls in all publicly released Greenland5 packages via dependencies
Home-page: https://gitlab.com/m-e-leypold/greenland5
Author: M E Leypold
Author-email: greenland5-sk01mq04ym43pr@m-e-leypold.de
License: GPLv3
Platform: UNKNOWN
Classifier: Development Status :: 3 - Alpha
Classifier: Environment :: Console
Classifier: Intended Audience :: Developers
Classifier: License :: OSI Approved :: GNU General Public License v3 (GPLv3)
Classifier: Operating System :: POSIX
Classifier: Programming Language :: Python
Requires-Python: >=3.7
License-File: LICENSE
License-File: AUTHORS
Requires-Dist: greenland5-base
